source_azure_blob_storage/__init__.py
source_azure_blob_storage/config_migrations.py
source_azure_blob_storage/run.py
source_azure_blob_storage/source.py
source_azure_blob_storage/spec.py
source_azure_blob_storage/stream_reader.py
airbyte_source_azure_blob_storage-0.8.11.dist-info/METADATA
airbyte_source_azure_blob_storage-0.8.11.dist-info/WHEEL
airbyte_source_azure_blob_storage-0.8.11.dist-info/entry_points.txt
airbyte_source_azure_blob_storage-0.8.11.dist-info/RECORD
