Metadata-Version: 2.1
Name: airbyte-source-azure-blob-storage
Version: 0.8.11
Summary: Source implementation for Azure Blob Storage.
Home-page: https://airbyte.com
License: ELv2
Author: Airbyte
Author-email: contact@airbyte.io
Requires-Python: >=3.11,<3.14
Classifier: License :: Other/Proprietary License
Classifier: Programming Language :: Python :: 3
Classifier: Programming Language :: Python :: 3.11
Classifier: Programming Language :: Python :: 3.12
Classifier: Programming Language :: Python :: 3.13
Requires-Dist: airbyte-cdk[file-based] (>=7.0.0,<8.0.0)
Requires-Dist: pytz (>=2024.1,<2025.0)
Requires-Dist: smart-open[azure] (==0.8.11)
Project-URL: Documentation, https://docs.airbyte.com/integrations/sources/azure-blob-storage
Project-URL: Repository, https://github.com/airbytehq/airbyte
